lab_instance_name/__init__.py
lab_instance_name/_version.py
lab_instance_name/handlers.py
lab_instance_name-0.1.0.data/data/share/jupyter/labextensions/lab_instance_name/build_log.json
lab_instance_name-0.1.0.data/data/share/jupyter/labextensions/lab_instance_name/package.json
lab_instance_name-0.1.0.data/data/share/jupyter/labextensions/lab_instance_name/static/lib_index_js.7a2ba57c255aba3000aa.js
lab_instance_name-0.1.0.data/data/share/jupyter/labextensions/lab_instance_name/static/lib_index_js.7a2ba57c255aba3000aa.js.map
lab_instance_name-0.1.0.data/data/share/jupyter/labextensions/lab_instance_name/static/remoteEntry.9a2d05b06089cc6cec70.js
lab_instance_name-0.1.0.data/data/share/jupyter/labextensions/lab_instance_name/static/remoteEntry.9a2d05b06089cc6cec70.js.map
lab_instance_name-0.1.0.data/data/share/jupyter/labextensions/lab_instance_name/static/style.js
lab_instance_name-0.1.0.data/data/share/jupyter/labextensions/lab_instance_name/static/style_index_js.87ce6b84a3af17047356.js
lab_instance_name-0.1.0.data/data/share/jupyter/labextensions/lab_instance_name/static/style_index_js.87ce6b84a3af17047356.js.map
lab_instance_name-0.1.0.data/data/share/jupyter/labextensions/lab_instance_name/install.json
lab_instance_name-0.1.0.dist-info/METADATA
lab_instance_name-0.1.0.dist-info/WHEEL
lab_instance_name-0.1.0.dist-info/licenses/LICENSE
lab_instance_name-0.1.0.dist-info/RECORD
