Metadata-Version: 2.1
Name: lab_instance_name
Version: 0.1.0
Summary: A JupyterLab extension for showing the lab instance name on the statusbar.
Project-URL: Homepage, https://github.com/PAICON-Code/jupyterlab-instance-name-extension
Project-URL: Bug Tracker, https://github.com/PAICON-Code/jupyterlab-instance-name-extension/issues
Project-URL: Repository, https://github.com/PAICON-Code/jupyterlab-instance-name-extension.git
Author-email: PAiCON <nishantamang1337@gmail.com>
License: BSD 3-Clause License
License-File: LICENSE
Classifier: Framework :: Jupyter
Classifier: Framework :: Jupyter :: JupyterLab
Classifier: Framework :: Jupyter :: JupyterLab :: 4
Classifier: Framework :: Jupyter :: JupyterLab :: Extensions
Classifier: Framework :: Jupyter :: JupyterLab :: Extensions :: Prebuilt
Classifier: License :: OSI Approved :: BSD License
Classifier: Programming Language :: Python
Classifier: Programming Language :: Python :: 3
Classifier: Programming Language :: Python :: 3.8
Classifier: Programming Language :: Python :: 3.9
Classifier: Programming Language :: Python :: 3.10
Classifier: Programming Language :: Python :: 3.11
Classifier: Programming Language :: Python :: 3.12
Requires-Python: >=3.8
